cjdlib/__init__.py
cjdlib-1.1.0.dist-info/LICENSE
cjdlib-1.1.0.dist-info/METADATA
cjdlib-1.1.0.dist-info/WHEEL
cjdlib-1.1.0.dist-info/top_level.txt
cjdlib-1.1.0.dist-info/RECORD
